easy_gpt_utils/__init__.py
easy_gpt_utils/embedding.py
easy_gpt_utils/gpt.py
easy_gpt_utils/vector_database.py
easy_gpt_utils_bak/__init__.py
easy_gpt_utils_bak/embedding.py
easy_gpt_utils_bak/gpt.py
easy_gpt_utils_bak/vector_database.py
easy_gpt_utils-0.1.10.dist-info/LICENSE
easy_gpt_utils-0.1.10.dist-info/METADATA
easy_gpt_utils-0.1.10.dist-info/WHEEL
easy_gpt_utils-0.1.10.dist-info/top_level.txt
easy_gpt_utils-0.1.10.dist-info/RECORD
